LICENSE
README.md
setup.py
src/hio/__init__.py
src/hio/__main__.py
src/hio/cli.py
src/hio/daemon.py
src/hio/hioing.py
src/hio.egg-info/PKG-INFO
src/hio.egg-info/SOURCES.txt
src/hio.egg-info/dependency_links.txt
src/hio.egg-info/entry_points.txt
src/hio.egg-info/not-zip-safe
src/hio.egg-info/requires.txt
src/hio.egg-info/top_level.txt
src/hio/base/__init__.py
src/hio/base/basing.py
src/hio/base/doing.py
src/hio/base/during.py
src/hio/base/filing.py
src/hio/base/multidoing.py
src/hio/base/tyming.py
src/hio/base/hier/__init__.py
src/hio/base/hier/acting.py
src/hio/base/hier/bagging.py
src/hio/base/hier/boxing.py
src/hio/base/hier/canning.py
src/hio/base/hier/durqing.py
src/hio/base/hier/dusqing.py
src/hio/base/hier/hiering.py
src/hio/base/hier/hogging.py
src/hio/base/hier/holding.py
src/hio/base/hier/needing.py
src/hio/core/__init__.py
src/hio/core/coring.py
src/hio/core/packeting.py
src/hio/core/wiring.py
src/hio/core/http/__init__.py
src/hio/core/http/clienting.py
src/hio/core/http/httping.py
src/hio/core/http/serving.py
src/hio/core/memo/__init__.py
src/hio/core/memo/memoing.py
src/hio/core/serial/__init__.py
src/hio/core/serial/serialing.py
src/hio/core/tcp/__init__.py
src/hio/core/tcp/clienting.py
src/hio/core/tcp/serving.py
src/hio/core/tcp/tcping.py
src/hio/core/udp/__init__.py
src/hio/core/udp/peermemoing.py
src/hio/core/udp/udping.py
src/hio/core/uxd/__init__.py
src/hio/core/uxd/peermemoing.py
src/hio/core/uxd/uxding.py
src/hio/core/wms/__init__.py
src/hio/core/wms/wmsing.py
src/hio/demo/__init__.py
src/hio/demo/web/__init__.py
src/hio/demo/web/demo_web.py
src/hio/demo/web/demoing.py
src/hio/help/__init__.py
src/hio/help/decking.py
src/hio/help/doming.py
src/hio/help/helping.py
src/hio/help/hicting.py
src/hio/help/mining.py
src/hio/help/naming.py
src/hio/help/ogling.py
src/hio/help/packing.py
src/hio/help/timing.py
tests/test_main.py