Metadata-Version: 2.4
Name: hio
Version: 0.7.19
Summary: Hierarchical Concurrency with Async IO
Home-page: https://github.com/ioflo/hio
Author: Samuel M. Smith
Author-email: smith.samuel.m@gmail.com
License: Apache Software License 2.0
Project-URL: Documentation, https://hio.readthedocs.io/
Project-URL: Changelog, https://hio.readthedocs.io/en/latest/changelog.html
Project-URL: Issue Tracker, https://github.com/ProSapien/hio/issues
Keywords: hierarchical concurrency,async io,rich contextual concurrency,structured concurrency
Classifier: Development Status :: 3 - Alpha
Classifier: Intended Audience :: Developers
Classifier: License :: OSI Approved :: Apache Software License
Classifier: Operating System :: Unix
Classifier: Operating System :: POSIX
Classifier: Operating System :: Microsoft :: Windows
Classifier: Programming Language :: Python :: 3.13
Classifier: Programming Language :: Python :: Implementation :: CPython
Classifier: Topic :: Utilities
Requires-Python: >=3.14.0
License-File: LICENSE
Requires-Dist: lmdb>=1.7.5
Requires-Dist: msgpack>=1.1.2
Requires-Dist: cbor2>=5.7.1
Requires-Dist: multidict>=6.7.0
Requires-Dist: falcon>=4.2.0
Requires-Dist: ordered-set>=4.1.0
Requires-Dist: pysodium>=0.7.18
Requires-Dist: blake3>=1.0.8
Dynamic: author
Dynamic: author-email
Dynamic: classifier
Dynamic: description
Dynamic: home-page
Dynamic: keywords
Dynamic: license
Dynamic: license-file
Dynamic: project-url
Dynamic: requires-dist
Dynamic: requires-python
Dynamic: summary
